mcp_demo_yashuashua/__init__.py
mcp_demo_yashuashua/server.py
yashuashua_mcp_server-0.2.3.dist-info/licenses/LICENSE
yashuashua_mcp_server-0.2.3.dist-info/METADATA
yashuashua_mcp_server-0.2.3.dist-info/WHEEL
yashuashua_mcp_server-0.2.3.dist-info/entry_points.txt
yashuashua_mcp_server-0.2.3.dist-info/top_level.txt
yashuashua_mcp_server-0.2.3.dist-info/RECORD
