Metadata-Version: 2.4
Name: yashuashua_mcp_server
Version: 0.2.3
Summary: A simple MCP (Model Context Protocol) server demo
Project-URL: Homepage, https://github.com/yourusername/mcp-demo
Project-URL: Repository, https://github.com/yourusername/mcp-demo.git
Project-URL: Issues, https://github.com/yourusername/mcp-demo/issues
Classifier: Development Status :: 3 - Alpha
Classifier: Intended Audience :: Developers
Classifier: License :: OSI Approved :: MIT License
Classifier: Programming Language :: Python :: 3
Classifier: Programming Language :: Python :: 3.8
Classifier: Programming Language :: Python :: 3.9
Classifier: Programming Language :: Python :: 3.10
Classifier: Programming Language :: Python :: 3.11
Classifier: Programming Language :: Python :: 3.12
Requires-Python: >=3.8
License-File: LICENSE
Requires-Dist: mcp>=0.1.0
Provides-Extra: dev
Requires-Dist: pytest>=7.0.0; extra == "dev"
Requires-Dist: build>=0.10.0; extra == "dev"
Requires-Dist: twine>=4.0.0; extra == "dev"
Dynamic: license-file
